short_activist_predictor/Filter.py
short_activist_predictor/__init__.py
short_activist_predictor/main.py
short_activist_predictor/owner.py
short_activist_predictor/predictor.py
short_activist_predictor/predictor_init.py
short_activist_predictor-1.0.2.dist-info/LICENSE.txt
short_activist_predictor-1.0.2.dist-info/METADATA
short_activist_predictor-1.0.2.dist-info/WHEEL
short_activist_predictor-1.0.2.dist-info/top_level.txt
short_activist_predictor-1.0.2.dist-info/RECORD
