Metadata-Version: 2.1
Name: short-activist-predictor
Version: 1.0.2
Summary: Short activists prediction
Home-page: https://github.com/DanGlChris/short_activist_predictor
Author: Daglox Kankwanda
Author-email: dagloxkankwenda@gmail.com
License: GPL-v3.0
Project-URL: Documentation, https://pyscaffold.org/
Platform: any
Classifier: Development Status :: 3 - Alpha
Classifier: Intended Audience :: Developers
Classifier: Topic :: Software Development :: Libraries :: Python Modules
Classifier: License :: OSI Approved :: GNU General Public License v3 (GPLv3)
Classifier: Programming Language :: Python :: 3.10
Classifier: Operating System :: Microsoft :: Windows
Classifier: Operating System :: POSIX :: Linux
License-File: LICENSE.txt
Requires-Dist: bertopic (>=0.15.0)
Requires-Dist: pdfplumber (>=0.10.2)
Requires-Dist: numpy (>=1.20.0)
Requires-Dist: pandas (>=1.1.5)
Requires-Dist: matplotlib (>=3.1.7)
Requires-Dist: nltk (>=3.8.1)
Requires-Dist: wordcloud (>=1.9.2)
Requires-Dist: transformers (>=4.34.0)
Requires-Dist: huggingface-hub (>=0.16.4)
Requires-Dist: pwinput (>=1.0.3)
Provides-Extra: testing
Requires-Dist: setuptools ; extra == 'testing'
Requires-Dist: pytest ; extra == 'testing'
Requires-Dist: pytest-cov ; extra == 'testing'
